rbrapi/__init__.py
rbrapi/errors.py
rbrapi/session.py
rbrapi/types.py
rbrapi-0.7.dist-info/licenses/LICENSE
rbrapi-0.7.dist-info/METADATA
rbrapi-0.7.dist-info/WHEEL
rbrapi-0.7.dist-info/top_level.txt
rbrapi-0.7.dist-info/RECORD
