Metadata-Version: 2.4
Name: rbrapi
Version: 0.7
Summary: Unofficial Python Client for Rocket Bot Royale Game API
Author-email: VWH <vwhe@proton.me>
Project-URL: Homepage, https://github.com/rocket-bot-royale/api
Project-URL: Issues, https://github.com/rocket-bot-royale/api/issues
Keywords: Rocket Bot Royale,game API,Unofficial API,Python library
Classifier: Programming Language :: Python :: 3
Classifier: License :: OSI Approved :: MIT License
Classifier: Operating System :: OS Independent
Requires-Python: >=3.8
License-File: LICENSE
Requires-Dist: requests
Dynamic: license-file
